deriv_api/__init__.py
deriv_api/cache.py
deriv_api/deriv_api.py
deriv_api/deriv_api_calls.py
deriv_api/easy_future.py
deriv_api/errors.py
deriv_api/in_memory.py
deriv_api/middlewares.py
deriv_api/streams_list.py
deriv_api/subscription_manager.py
deriv_api/utils.py
python_deriv_api-0.1.6.dist-info/LICENSE
python_deriv_api-0.1.6.dist-info/METADATA
python_deriv_api-0.1.6.dist-info/WHEEL
python_deriv_api-0.1.6.dist-info/top_level.txt
python_deriv_api-0.1.6.dist-info/RECORD
