Metadata-Version: 2.1
Name: python-deriv-api
Version: 0.1.6
Summary: Python bindings for deriv.com websocket API
Home-page: https://github.com/binary-com/python-deriv-api
Author: Deriv Group Services Ltd
Author-email: learning+python@deriv.com
License: MIT
Project-URL: Bug Tracker, https://github.com/binary-com/python-deriv-api/issues
Project-URL: Documentation, https://binary-com.github.io/python-deriv-api
Project-URL: Source Code, https://github.com/binary-com/python-deriv-api
Project-URL: Changelog, https://github.com/binary-com/python-deriv-api/blob/master/CHANGELOG.md
Classifier: Programming Language :: Python :: 3
Classifier: Operating System :: OS Independent
Requires-Python: >=3.9.6, !=3.9.7
License-File: LICENSE
